[{"name":"Parthiv Patel †","run":"0","balls":"3","fours":"0","sixes":"0","sr":"0.00"},{"name":"Virat Kohli (c)","run":"16","balls":"7","fours":"2","sixes":"1","sr":"228.57"},{"name":"AB de Villiers ","run":"1","balls":"2","fours":"0","sixes":"0","sr":"50.00"},{"name":"Shimron Hetmyer ","run":"75","balls":"47","fours":"4","sixes":"6","sr":"159.57"},{"name":"Gurkeerat Singh Mann ","run":"65","balls":"48","fours":"8","sixes":"1","sr":"135.41"},{"name":"Colin de Grandhomme ","run":"3","balls":"4","fours":"0","sixes":"0","sr":"75.00"},{"name":"Washington Sundar ","run":"0","balls":"1","fours":"0","sixes":"0","sr":"0.00"},{"name":"Umesh Yadav ","run":"9","balls":"4","fours":"2","sixes":"0","sr":"225.00"}]