[{"name":"Krishnappa Gowtham","over":"4","maiden":"0","runs":"16","wickets":"0","economy":"4.00"},{"name":"Varun Aaron","over":"2","maiden":"0","runs":"21","wickets":"0","economy":"10.50"},{"name":"Oshane Thomas","over":"1","maiden":"0","runs":"13","wickets":"0","economy":"13.00"},{"name":"Ish Sodhi","over":"3.1","maiden":"1","runs":"26","wickets":"3","economy":"8.21"},{"name":"Shreyas Gopal","over":"4","maiden":"0","runs":"21","wickets":"2","economy":"5.25"},{"name":"Riyan Parag","over":"1","maiden":"0","runs":"14","wickets":"0","economy":"14.00"},{"name":"Stuart Binny","over":"1","maiden":"0","runs":"6","wickets":"0","economy":"6.00"}]